[
	{
		"name": "Civilian Convoy",
		"unitType": "Civilian",
		"movement": 3,
		"cost": 106,
		"uniques": [
			"Founds a new city <in [{non-[Tunneled Mountain]} {non-[Fissure]} {Land}] tiles> <by consuming this unit>",
			"[+15] HP when healing",
			"All adjacent units heal [+15] HP when healing",
			"Excess Food converted to Production when under construction",
			"Requires at least [2] population"
		],
		"hurryCostModifier": 20
	},
	{
		"name": "Military Engineer",
		"unitType": "Civilian",
		"movement": 2,
		"cost": 120,
		"requiredTech": "Engineering",
		"uniques": ["Can pass through impassable tiles",
			"Can build [All Road] improvements on tiles",
			"Can instantly construct a [Fort] improvement <[2] times> <after which this unit is consumed>",
			"Turn this tile into a [Tunneled Mountain] tile <in [Mountain] tiles> <by consuming this unit>"]
	}
]
