[
	{
		"name": "Shock Worker",
		"replaces": "Worker",
		"uniqueTo": "Crimson Line",
		"unitType": "Civilian",
		"movement": 2,
		"cost": 70,
		"hurryCostModifier": 20,
		"upgradesTo": "Mechanized Worker",
		"uniques": ["Can build [Land] improvements on tiles",
			"[-25]% construction time for [All] improvements",
			"Ignores terrain cost",
			"Automation is a primary action"]
	},
	{
		"name": "Kommissar",
		"replaces": "Censor",
		"uniqueTo": "Crimson Line",
		"unitType": "Shooter",
		"range": 1,
		"movement": 2,
		"strength": 30,
		"rangedStrength": 24,
		"interceptRange": 1,
		"cost": 50,
		"upgradesTo": "Rifleman",
		"uniques": ["Personnel",
			"Can be purchased for [200] [Gold] [in all non-occupied cities]",
			"[+10]% Strength bonus for [Military] units within [2] tiles",
			"[-33]% Strength <vs cities>",
			"Prevents spreading of religion to the city it is next to",
			"Can remove other religions from cities <in [Friendly] tiles> <[2] times> <after which this unit is consumed>",
			"[+1] Sight",
			"Unbuildable",
			"Religious Unit",
			"Hidden when religion is disabled"],
		"attackSound": "shot"
	},
	{
		"name": "Volt Driver",
		"replaces": "Crossbowman",
		"uniqueTo": "Crimson Line",
		"unitType": "Shooter",
		"range": 2,
		"movement": 2,
		"strength": 35,
		"rangedStrength": 30,
		"cost": 35,
		"hurryCostModifier": 20,
		"requiredTech": "Steel",
		"obsoleteTech": "Rifling",
		"upgradesTo": "Rifleman",
		"uniques": [
			"Low Tech",
			"Must set up to ranged attack",
			"[+50]% Strength <vs [Low Tech] units> <when attacking>",
			"[+50]% Strength <vs [Barbarian] units> <when attacking>"
		],
		"attackSound": "shot"
	},
	{
		"name": "Armored Train",
		"unitType": "Armor",
		"uniqueTo": "Crimson Line",
		"movement": 5,
		"strength": 45,
		"cost": 150,
		"requiredTech": "Steam Power",
		"upgradesTo": "Tank",
		"obsoleteTech": "Combined Arms",
		"uniques": ["[+25]% Strength <vs [Low Tech] units> <when attacking>",
			"[+25]% Strength <vs [Personnel] units> <when attacking>",
			"[+50]% Strength <vs cities> <when attacking>",
			"Can move after attacking",
			"No defensive terrain bonus",
			"[+1] Movement <after discovering [Railroads]>",
			"Consumes [1] [Power]"],
		"hurryCostModifier": 20,
		"attackSound": "machinegun"
	},
	{
		"name": "RCB Conscript",
		"unitType": "Scrapper",
		"uniqueTo": "Crimson Line",
		"replaces": "NBC Conscript",
		"movement": 2,
		"strength": 36,
		"interceptRange": 1,
		"cost": 125,
		"requiredTech": "Plastics",
		"hurryCostModifier": 20,
		"uniques": [
			"Personnel",
			"Enslaved",
			"Only available <if [Factory] is constructed>",
			"[+20]% Strength <when fighting in [Friendly Land] tiles>",
			"[-25]% construction time for [All] improvements",
			"Can build [All Road] improvements on tiles",
			"Can build [Fort] improvements on tiles",
			"Can build [Trench] improvements on tiles",
			"Only available <with [Slaves]>",
			"Consumes [1] [Slaves]",
			"Never appears as a Barbarian unit"
		],
		"promotions": ["Gas Mask"],
		"attackSound": "machinegun"
	},
	{
		"name": "RCB Infantry",
		"unitType": "Scrapper",
		"uniqueTo": "Crimson Line",
		"replaces": "NBC Infantry",
		"movement": 2,
		"strength": 45,
		"interceptRange": 1,
		"cost": 225,
		"requiredTech": "Plastics",
		"upgradesTo": "Exo-Trooper",
		"hurryCostModifier": 20,
		"promotions": ["Gas Mask"],
		"uniques": ["Personnel", "Consumes [1] [Weapons]",
			"[+15]% Strength <when fighting in [Friendly Land] tiles>",
			"[+25]% Strength <vs [City-State] units>",
			"[+25]% Strength <vs cities>"],
		"attackSound": "machinegun"
	},
	{
		"name": "Crimson Sniper",
		"unitType": "Shooter",
		"uniqueTo": "Crimson Line",
		"replaces": "NBC Marksman",
		"range": 1,
		"movement": 2,
		"strength": 40,
		"rangedStrength": 45,
		"interceptRange": 1,
		"cost": 225,
		"requiredTech": "Plastics",
		"upgradesTo": "Black Ops",
		"hurryCostModifier": 20,
		"uniques": ["Personnel", "Only available <if [Factory] is constructed>", "Consumes [1] [Weapons]"],
		"promotions": ["Reconnaissance I", "Gas Mask", "Thermoptic Camouflage"],
		"attackSound": "sniper"
	}
]